pytennisscorer/__init__.py
pytennisscorer/configs.py
pytennisscorer/formatter.py
pytennisscorer/models.py
pytennisscorer/progression.py
pytennisscorer/scorer.py
pytennisscorer/scoring.py
pytennisscorer-0.1.0.dist-info/METADATA
pytennisscorer-0.1.0.dist-info/WHEEL
pytennisscorer-0.1.0.dist-info/RECORD
